epdb/__init__.py
epdb/epdb_client.py
epdb/epdb_nose.py
epdb/epdb_server.py
epdb/epdb_stackutil.py
epdb/erlcompleter.py
epdb/formattrace.py
epdb-0.15.1.dist-info/DESCRIPTION.rst
epdb-0.15.1.dist-info/METADATA
epdb-0.15.1.dist-info/RECORD
epdb-0.15.1.dist-info/WHEEL
epdb-0.15.1.dist-info/entry_points.txt
epdb-0.15.1.dist-info/metadata.json
epdb-0.15.1.dist-info/top_level.txt
