Metadata-Version: 1.1
Name: epdb
Version: 0.15.1
Summary: Enhanced Python Debugger
Home-page: https://github.com/sassoftware/epdb
Author: SAS Institute, Inc.
Author-email: elliot.peele@sas.com
License: MIT
Keywords: debugger pdb remote
Platform: Posix; MacOS X; Windows
Classifier: Operating System :: OS Independent
Classifier: Intended Audience :: Developers
Classifier: License :: OSI Approved :: MIT License
Classifier: Topic :: Software Development :: Debuggers
Classifier: Programming Language :: Python :: 2
Classifier: Programming Language :: Python :: 3
